wagtail_draftail_anchors/__init__.py
wagtail_draftail_anchors/apps.py
wagtail_draftail_anchors/rich_text.py
wagtail_draftail_anchors/wagtail_hooks.py
wagtail_draftail_anchors/static/wagtaildraftailanchors/js/wagtail-draftail-anchor.js
wagtail_draftail_anchors/templates/wagtaildraftailanchors/icons/anchor.svg
wagtail_draftail_anchors-0.7.0.dist-info/METADATA
wagtail_draftail_anchors-0.7.0.dist-info/WHEEL
wagtail_draftail_anchors-0.7.0.dist-info/top_level.txt
wagtail_draftail_anchors-0.7.0.dist-info/RECORD
