Metadata-Version: 2.4
Name: wagtail_draftail_anchors
Version: 0.7.0
Summary: A Draftail extension to add anchor identifiers to rich text
Home-page: https://github.com/wagtail-nest/wagtail_draftail_anchors
Author: Wagtail Core Team
Author-email: hello@wagtail.org
Classifier: Programming Language :: Python :: 3
Classifier: License :: OSI Approved :: MIT License
Classifier: Operating System :: OS Independent
Classifier: Framework :: Wagtail :: 2
Classifier: Framework :: Wagtail :: 3
Classifier: Framework :: Wagtail :: 4
Classifier: Framework :: Wagtail :: 5
Classifier: Framework :: Wagtail :: 6
Requires-Python: >=3.6
Requires-Dist: wagtail>2.9
Dynamic: author
Dynamic: author-email
Dynamic: classifier
Dynamic: description
Dynamic: description-content-type
Dynamic: home-page
Dynamic: requires-dist
Dynamic: requires-python
Dynamic: summary
